odoo/addons/partner_lastname_uppercase/README.rst
odoo/addons/partner_lastname_uppercase/__init__.py
odoo/addons/partner_lastname_uppercase/__manifest__.py
odoo/addons/partner_lastname_uppercase/data/actions.xml
odoo/addons/partner_lastname_uppercase/i18n/it.po
odoo/addons/partner_lastname_uppercase/i18n/partner_lastname_uppercase.pot
odoo/addons/partner_lastname_uppercase/models/__init__.py
odoo/addons/partner_lastname_uppercase/models/res_config_settings.py
odoo/addons/partner_lastname_uppercase/models/res_partner.py
odoo/addons/partner_lastname_uppercase/readme/CONFIGURE.rst
odoo/addons/partner_lastname_uppercase/readme/CONTRIBUTORS.rst
odoo/addons/partner_lastname_uppercase/readme/DESCRIPTION.rst
odoo/addons/partner_lastname_uppercase/readme/USAGE.rst
odoo/addons/partner_lastname_uppercase/static/description/icon.png
odoo/addons/partner_lastname_uppercase/static/description/index.html
odoo/addons/partner_lastname_uppercase/tests/__init__.py
odoo/addons/partner_lastname_uppercase/tests/test_res_partner.py
odoo/addons/partner_lastname_uppercase/views/res_config_settings.xml
odoo_addon_partner_lastname_uppercase-16.0.1.0.1.5.dist-info/METADATA
odoo_addon_partner_lastname_uppercase-16.0.1.0.1.5.dist-info/WHEEL
odoo_addon_partner_lastname_uppercase-16.0.1.0.1.5.dist-info/top_level.txt
odoo_addon_partner_lastname_uppercase-16.0.1.0.1.5.dist-info/RECORD
